{"/art/exhibits/parc1994algoart.html":"http://www2.cs.uregina.ca/~hepting/projects/fractals/exhibitions/1994-PARC-Algorithmic-Art-Show.html","/art/exhibits/teck1995mathart/":"http://www2.cs.uregina.ca/~hepting/projects/fractals/exhibitions/1995-MATH-ART-at-SFU-Teck-Gallery.html","/art/exhibits/teck1995mathart/index.html":"http://www2.cs.uregina.ca/~hepting/projects/fractals/exhibitions/1995-MATH-ART-at-SFU-Teck-Gallery.html","/art/exhibits/teck1995mathart/fiery.html":"http://www2.cs.uregina.ca/~hepting/projects/fractals/exhibitions/1995-MATH-ART-at-SFU-Teck-Gallery.html","/art/AoFcals/1995/aug.html":"http://www2.cs.uregina.ca/~hepting/projects/fractals/calendars/1995.html","/teaching/201810/":"http://www2.cs.uregina.ca/~hepting/teaching/schedule/201810.html","/403.html":"http://www2.cs.uregina.ca/~hepting/HTTPerrors/403.html","/404.html":"http://www2.cs.uregina.ca/~hepting/HTTPerrors/404.html","/500.html":"http://www2.cs.uregina.ca/~hepting/HTTPerrors/500.html","/about/personal/daryls/":"http://www2.cs.uregina.ca/~hepting/about/","/about/personal/heptings/":"http://www2.cs.uregina.ca/~hepting/about/","/personal/index.html":"http://www2.cs.uregina.ca/~hepting/about/","/art/AoFcals/":"http://www2.cs.uregina.ca/~hepting/projects/fractals/calendars/","/art/":"http://www2.cs.uregina.ca/~hepting/projects/fractals/","/research/web/math-of-art/index.html":"http://www2.cs.uregina.ca/~hepting/projects/fractals/","/research/web/math-of-art/":"http://www2.cs.uregina.ca/~hepting/projects/fractals/","/research/web/words/history.html":"http://www2.cs.uregina.ca/~hepting/projects/pictures-worth/","/research/web/words/index.html":"http://www2.cs.uregina.ca/~hepting/projects/pictures-worth/","/proverbial/history.html":"http://www2.cs.uregina.ca/~hepting/projects/pictures-worth/","/research/works.html":"http://www2.cs.uregina.ca/~hepting/research/works/","/assets/pdfs/works/2006-00-C-CMiSoID.pdf":"http://www2.cs.uregina.ca/~hepting/research/works/","/research/external.html":"http://www2.cs.uregina.ca/~hepting/research/","/research/pubs/":"http://www2.cs.uregina.ca/~hepting/research/","/teaching/cs110/201810/code-meetings/33-const-ref.cpp":"http://www2.cs.uregina.ca/~hepting/teaching/CS-110/201810/","/teaching/cs110/201810/code-meetings/31-ambiguous.cpp":"http://www2.cs.uregina.ca/~hepting/teaching/CS-110/201810/","/teaching/cs205-325/201610/":"http://www2.cs.uregina.ca/~hepting/teaching/CS-205/","/teaching/cs280/201510/":"http://www2.cs.uregina.ca/~hepting/teaching/CS-280/","/teaching/cs280/201610/":"http://www2.cs.uregina.ca/~hepting/teaching/CS-280/","/teaching/cs280/201710/":"http://www2.cs.uregina.ca/~hepting/teaching/CS-280/","/cs280/201610/":"http://www2.cs.uregina.ca/~hepting/teaching/CS-280/","/cs305-428-828/201630/":"http://www2.cs.uregina.ca/~hepting/teaching/CS-428+828/","/teaching/cs499+900/":"http://www2.cs.uregina.ca/~hepting/teaching/CS-499+900/","/teaching/cs499%2B900/":"http://www2.cs.uregina.ca/~hepting/teaching/CS-499+900/","/teaching/201320.html":"http://www2.cs.uregina.ca/~hepting/teaching/","/teaching/sem/":"http://www2.cs.uregina.ca/~hepting/teaching/schedule/","/teaching/bysemester.html":"http://www2.cs.uregina.ca/~hepting/teaching/","/teaching/201810.html":"http://www2.cs.uregina.ca/~hepting/teaching/","/teaching/cs215/":"http://www2.cs.uregina.ca/~hepting/teaching/","/teach/":"http://www2.cs.uregina.ca/~hepting/teaching/","/teach/resources/":"http://www2.cs.uregina.ca/~hepting/teaching/","/teach/resources/scenarios.html":"http://www2.cs.uregina.ca/~hepting/teaching/","/research/inspiration.html":"http://www2.cs.uregina.ca/~hepting/research/inspirations.html","/teach/philosophy.html":"http://www2.cs.uregina.ca/~hepting/teaching/philosophy.html"}